sworn/__init__.py
sworn/commitment.py
sworn/contract.py
sworn/execution.py
sworn/types.py
sworn/observability/datadog.py
sworn/observability/observer.py
sworn/verifiers/semantic_verifier.py
sworn-0.1.1.dist-info/licenses/LICENSE
sworn-0.1.1.dist-info/METADATA
sworn-0.1.1.dist-info/WHEEL
sworn-0.1.1.dist-info/top_level.txt
sworn-0.1.1.dist-info/RECORD
