Metadata-Version: 2.4
Name: sworn
Version: 0.1.1
Summary: Unopinionated contract-based verification for AI agents
Author: Kavish Sathia
License: MIT
Requires-Python: >=3.11
License-File: LICENSE
Requires-Dist: google-adk
Requires-Dist: ddtrace
Requires-Dist: tenacity
Provides-Extra: dev
Requires-Dist: pytest; extra == "dev"
Requires-Dist: pytest-cov; extra == "dev"
Dynamic: license-file
